[{"date":"2019-12-31","count":27,"reporting":[1,240]},{"date":"2020-01-03","count":17,"reporting":[1,240]},{"date":"2020-01-05","count":15,"reporting":[1,240]},{"date":"2020-01-09","count":0,"reporting":[152,240]},{"date":"2020-01-10","count":-18,"reporting":[1,240]},{"date":"2020-01-11","count":0,"reporting":[1,240]},{"date":"2020-01-12","count":0,"reporting":[1,240]},{"date":"2020-01-13","count":1,"reporting":[4,240]},{"date":"2020-01-14","count":0,"reporting":[1,240]},{"date":"2020-01-15","count":0,"reporting":[1,240]},{"date":"2020-01-16","count":5,"reporting":[2,240]},{"date":"2020-01-17","count":18,"reporting":[2,240]},{"date":"2020-01-18","count":59,"reporting":[1,240]},{"date":"2020-01-19","count":78,"reporting":[2,240]},{"date":"2020-01-20","count":93,"reporting":[1,240]},{"date":"2020-01-21","count":151,"reporting":[3,240]},{"date":"2020-01-22","count":135,"reporting":[4,240]},{"date":"2020-01-23","count":264,"reporting":[5,240]},{"date":"2020-01-24","count":469,"reporting":[9,240]},{"date":"2020-01-25","count":700,"reporting":[5,240]},{"date":"2020-01-26","count":786,"reporting":[10,240]},{"date":"2020-01-27","count":1778,"reporting":[8,240]},{"date":"2020-01-28","count":1480,"reporting":[9,240]},{"date":"2020-01-29","count":1754,"reporting":[9,240]},{"date":"2020-01-30","count":2003,"reporting":[15,240]},{"date":"2020-01-31","count":2130,"reporting":[14,240]},{"date":"2020-02-01","count":2603,"reporting":[10,240]},{"date":"2020-02-02","count":2836,"reporting":[9,240]},{"date":"2020-02-03","count":3239,"reporting":[5,240]},{"date":"2020-02-04","count":3925,"reporting":[13,240]},{"date":"2020-02-05","count":3725,"reporting":[9,240]},{"date":"2020-02-06","count":3202,"reporting":[11,240]},{"date":"2020-02-07","count":3397,"reporting":[7,240]},{"date":"2020-02-08","count":2678,"reporting":[9,240]},{"date":"2020-02-09","count":3001,"reporting":[10,240]},{"date":"2020-02-10","count":2546,"reporting":[7,240]},{"date":"2020-02-11","count":2070,"reporting":[8,240]},{"date":"2020-02-12","count":15158,"reporting":[6,240]},{"date":"2020-02-13","count":4110,"reporting":[7,240]},{"date":"2020-02-14","count":2661,"reporting":[5,240]},{"date":"2020-02-15","count":2098,"reporting":[7,240]},{"date":"2020-02-16","count":2132,"reporting":[7,240]},{"date":"2020-02-17","count":2004,"reporting":[7,240]},{"date":"2020-02-18","count":1866,"reporting":[5,240]},{"date":"2020-02-19","count":526,"reporting":[7,240]},{"date":"2020-02-20","count":996,"reporting":[8,240]},{"date":"2020-02-21","count":1070,"reporting":[14,240]},{"date":"2020-02-22","count":904,"reporting":[9,240]},{"date":"2020-02-23","count":517,"reporting":[9,240]},{"date":"2020-02-24","count":930,"reporting":[16,240]},{"date":"2020-02-25","count":677,"reporting":[21,240]},{"date":"2020-02-26","count":936,"reporting":[26,240]},{"date":"2020-02-27","count":1330,"reporting":[30,240]},{"date":"2020-02-28","count":2113,"reporting":[38,240]},{"date":"2020-02-29","count":1408,"reporting":[34,240]},{"date":"2020-03-01","count":2460,"reporting":[39,240]},{"date":"2020-03-02","count":1861,"reporting":[45,240]},{"date":"2020-03-03","count":2190,"reporting":[35,240]},{"date":"2020-03-04","count":2322,"reporting":[47,240]},{"date":"2020-03-05","count":2872,"reporting":[49,240]},{"date":"2020-03-06","count":3781,"reporting":[66,240]},{"date":"2020-03-07","count":3950,"reporting":[74,240]},{"date":"2020-03-08","count":3973,"reporting":[74,240]},{"date":"2020-03-09","count":4550,"reporting":[79,240]},{"date":"2020-03-10","count":4893,"reporting":[85,240]},{"date":"2020-03-11","count":6875,"reporting":[79,240]},{"date":"2020-03-12","count":8439,"reporting":[84,240]},{"date":"2020-03-13","count":10969,"reporting":[116,240]},{"date":"2020-03-14","count":10773,"reporting":[105,240]},{"date":"2020-03-15","count":12872,"reporting":[108,240]},{"date":"2020-03-16","count":13249,"reporting":[114,240]},{"date":"2020-03-17","count":15850,"reporting":[122,240]},{"date":"2020-03-18","count":20673,"reporting":[137,240]},{"date":"2020-03-19","count":26397,"reporting":[133,240]},{"date":"2020-03-20","count":29854,"reporting":[133,240]},{"date":"2020-03-21","count":30188,"reporting":[144,240]},{"date":"2020-03-22","count":33043,"reporting":[185,240]},{"date":"2020-03-23","count":39110,"reporting":[147,240]},{"date":"2020-03-24","count":43551,"reporting":[155,240]},{"date":"2020-03-25","count":49948,"reporting":[156,240]},{"date":"2020-03-26","count":60635,"reporting":[150,240]},{"date":"2020-03-27","count":64576,"reporting":[147,240]},{"date":"2020-03-28","count":66473,"reporting":[146,240]},{"date":"2020-03-29","count":57398,"reporting":[195,240]},{"date":"2020-03-30","count":57112,"reporting":[199,240]},{"date":"2020-03-31","count":73037,"reporting":[201,240]},{"date":"2020-04-01","count":84074,"reporting":[231,240]},{"date":"2020-04-02","count":73885,"reporting":[234,240]},{"date":"2020-04-03","count":88210,"reporting":[233,240]},{"date":"2020-04-04","count":80294,"reporting":[234,240]},{"date":"2020-04-05","count":69481,"reporting":[235,240]},{"date":"2020-04-06","count":67928,"reporting":[233,240]},{"date":"2020-04-07","count":73930,"reporting":[233,240]},{"date":"2020-04-08","count":83751,"reporting":[235,240]},{"date":"2020-04-09","count":85877,"reporting":[236,240]},{"date":"2020-04-10","count":92203,"reporting":[239,240]},{"date":"2020-04-11","count":79497,"reporting":[240,240]},{"date":"2020-04-12","count":99357,"reporting":[240,240]},{"date":"2020-04-13","count":73396,"reporting":[240,240]},{"date":"2020-04-14","count":74802,"reporting":[239,240]},{"date":"2020-04-15","count":82515,"reporting":[239,240]},{"date":"2020-04-16","count":90467,"reporting":[240,240]},{"date":"2020-04-17","count":87685,"reporting":[240,240]},{"date":"2020-04-18","count":80336,"reporting":[240,240]},{"date":"2020-04-19","count":73794,"reporting":[240,240]},{"date":"2020-04-20","count":75537,"reporting":[239,240]},{"date":"2020-04-21","count":73573,"reporting":[240,240]},{"date":"2020-04-22","count":80088,"reporting":[239,240]},{"date":"2020-04-23","count":83217,"reporting":[240,240]},{"date":"2020-04-24","count":104983,"reporting":[240,240]},{"date":"2020-04-25","count":89821,"reporting":[240,240]},{"date":"2020-04-26","count":73460,"reporting":[240,240]},{"date":"2020-04-27","count":66486,"reporting":[239,240]},{"date":"2020-04-28","count":77960,"reporting":[239,240]},{"date":"2020-04-29","count":74785,"reporting":[240,240]},{"date":"2020-04-30","count":81708,"reporting":[240,240]},{"date":"2020-05-01","count":90615,"reporting":[210,240]},{"date":"2020-05-02","count":83403,"reporting":[240,240]},{"date":"2020-05-03","count":77241,"reporting":[240,240]},{"date":"2020-05-04","count":75094,"reporting":[223,240]},{"date":"2020-05-05","count":82824,"reporting":[240,240]},{"date":"2020-05-06","count":88337,"reporting":[235,240]},{"date":"2020-05-07","count":94603,"reporting":[237,240]},{"date":"2020-05-08","count":92149,"reporting":[237,240]},{"date":"2020-05-09","count":90129,"reporting":[233,240]},{"date":"2020-05-10","count":77640,"reporting":[234,240]},{"date":"2020-05-11","count":71273,"reporting":[234,240]},{"date":"2020-05-12","count":80068,"reporting":[240,240]},{"date":"2020-05-13","count":85319,"reporting":[224,240]},{"date":"2020-05-14","count":96931,"reporting":[236,240]},{"date":"2020-05-15","count":98177,"reporting":[236,240]},{"date":"2020-05-16","count":91553,"reporting":[230,240]},{"date":"2020-05-17","count":81397,"reporting":[234,240]},{"date":"2020-05-18","count":87010,"reporting":[235,240]},{"date":"2020-05-19","count":96173,"reporting":[234,240]},{"date":"2020-05-20","count":100288,"reporting":[235,240]},{"date":"2020-05-21","count":105220,"reporting":[234,240]},{"date":"2020-05-22","count":107997,"reporting":[226,240]},{"date":"2020-05-23","count":99989,"reporting":[210,240]},{"date":"2020-05-24","count":95717,"reporting":[223,240]},{"date":"2020-05-25","count":87883,"reporting":[227,240]},{"date":"2020-05-26","count":96109,"reporting":[227,240]},{"date":"2020-05-27","count":103270,"reporting":[229,240]},{"date":"2020-05-28","count":117574,"reporting":[224,240]},{"date":"2020-05-29","count":120747,"reporting":[230,240]},{"date":"2020-05-30","count":126234,"reporting":[226,240]},{"date":"2020-05-31","count":107197,"reporting":[229,240]},{"date":"2020-06-01","count":101248,"reporting":[228,240]},{"date":"2020-06-02","count":113690,"reporting":[227,240]},{"date":"2020-06-03","count":119258,"reporting":[219,240]},{"date":"2020-06-04","count":131362,"reporting":[210,240]},{"date":"2020-06-05","count":134488,"reporting":[224,240]},{"date":"2020-06-06","count":126289,"reporting":[233,240]},{"date":"2020-06-07","count":111599,"reporting":[231,240]},{"date":"2020-06-08","count":107925,"reporting":[226,240]},{"date":"2020-06-09","count":124445,"reporting":[226,240]},{"date":"2020-06-10","count":134664,"reporting":[227,240]},{"date":"2020-06-11","count":138214,"reporting":[228,240]},{"date":"2020-06-12","count":138776,"reporting":[222,240]},{"date":"2020-06-13","count":134424,"reporting":[226,240]},{"date":"2020-06-14","count":124975,"reporting":[226,240]},{"date":"2020-06-15","count":121839,"reporting":[230,240]},{"date":"2020-06-16","count":139756,"reporting":[229,240]},{"date":"2020-06-17","count":174916,"reporting":[229,240]},{"date":"2020-06-18","count":141768,"reporting":[236,240]},{"date":"2020-06-19","count":178571,"reporting":[228,240]},{"date":"2020-06-20","count":160709,"reporting":[231,240]},{"date":"2020-06-21","count":129686,"reporting":[223,240]},{"date":"2020-06-22","count":139521,"reporting":[233,240]},{"date":"2020-06-23","count":162169,"reporting":[231,240]},{"date":"2020-06-24","count":172363,"reporting":[229,240]},{"date":"2020-06-25","count":180092,"reporting":[232,240]},{"date":"2020-06-26","count":190878,"reporting":[227,240]},{"date":"2020-06-27","count":177562,"reporting":[214,240]},{"date":"2020-06-28","count":164666,"reporting":[219,240]},{"date":"2020-06-29","count":157603,"reporting":[228,240]},{"date":"2020-06-30","count":176552,"reporting":[230,240]},{"date":"2020-07-01","count":217831,"reporting":[236,240]},{"date":"2020-07-02","count":206347,"reporting":[235,240]},{"date":"2020-07-03","count":205284,"reporting":[207,240]},{"date":"2020-07-04","count":191278,"reporting":[200,240]},{"date":"2020-07-05","count":177836,"reporting":[195,240]},{"date":"2020-07-06","count":155801,"reporting":[202,240]},{"date":"2020-07-07","count":24244,"reporting":[34,240]}]